[{"id":1,"name":"Test Change","email":"change@gmail.com","address":"Test Change","contact_no":"09090909090","update_date":"2023-08-03 20:27:29","create_date":"2023-08-03 20:27:22","deleted_date":"2023-08-03 20:27:29"},{"id":2,"name":"test 1","email":"1@test.com","address":"123","contact_no":"123","update_date":"2023-08-04 20:14:32","create_date":"2023-08-04 20:14:32","deleted_date":null},{"id":3,"name":"test 2","email":"dest","address":"rest","contact_no":"1234","update_date":"2023-08-04 20:14:57","create_date":"2023-08-04 20:14:57","deleted_date":null}]